pBaseParams/__init__.py
pBaseParams/pBaseParams.py
mynelibs-1.0.0.dist-info/METADATA
mynelibs-1.0.0.dist-info/WHEEL
mynelibs-1.0.0.dist-info/top_level.txt
mynelibs-1.0.0.dist-info/RECORD
