Metadata-Version: 2.4
Name: mynelibs
Version: 1.0.0
Summary: A simple Python library
Author: PAT
Author-email: PAT <patdev495@gmail.com>
License: MIT
Requires-Python: >=3.8
Requires-Dist: numpy
Requires-Dist: watchdog
Requires-Dist: PyYAML
Requires-Dist: opencv-python
Dynamic: author
Dynamic: description-content-type
Dynamic: requires-python
